openguanaco/__init__.py
openguanaco-0.0.1.dist-info/METADATA
openguanaco-0.0.1.dist-info/WHEEL
openguanaco-0.0.1.dist-info/licenses/LICENSE
openguanaco-0.0.1.dist-info/RECORD
