Metadata-Version: 2.1
Name: openguanaco
Version: 0.0.1
Summary: Coming soon!
Project-URL: Homepage, https://github.com/togethercomputer/openguanaco
Project-URL: Bug Tracker, https://github.com/togethercomputer/openguanaco/issues
Author-email: Together Computer <community@together.xyz>
License-File: LICENSE
Classifier: License :: OSI Approved :: Apache Software License
Classifier: Operating System :: POSIX :: Linux
Classifier: Programming Language :: Python :: 3
Requires-Python: >=3.10
